scietex/service/__init__.py
scietex/service/basic_async_worker.py
scietex/service/logo.py
scietex/service/py.typed
scietex/service/redis_async_worker.py
scietex/service/valkey_async_worker.py
scietex/service/version.py
scietex_service-0.1.5.dist-info/licenses/LICENSE
scietex_service-0.1.5.dist-info/METADATA
scietex_service-0.1.5.dist-info/WHEEL
scietex_service-0.1.5.dist-info/top_level.txt
scietex_service-0.1.5.dist-info/RECORD
