Metadata-Version: 2.4
Name: scietex.service
Version: 0.1.5
Summary: Scietex service daemon impementation
Author-email: Anton Bondarenko <bond.anton@gmail.com>
License: MIT License
Project-URL: Homepage, https://github.com/bond-anton/scietex.service
Project-URL: Bug Tracker, https://github.com/bond-anton/scietex.service/issues
Classifier: Programming Language :: Python :: 3
Classifier: License :: OSI Approved :: MIT License
Classifier: Operating System :: OS Independent
Requires-Python: >=3.9
License-File: LICENSE
Requires-Dist: pyyaml
Requires-Dist: scietex.logging>=0.1.1
Provides-Extra: redis
Requires-Dist: scietex.logging[redis]>=0.1.0; extra == "redis"
Requires-Dist: redis>=4.2.0; extra == "redis"
Provides-Extra: valkey
Requires-Dist: scietex.logging[valkey]>=0.1.0; extra == "valkey"
Requires-Dist: valkey-glide~=2.0.0; extra == "valkey"
Provides-Extra: dev
Requires-Dist: redis>=4.2.0; extra == "dev"
Requires-Dist: valkey-glide~=2.0.0; extra == "dev"
Provides-Extra: test
Requires-Dist: flake8; extra == "test"
Requires-Dist: pytest; extra == "test"
Requires-Dist: pytest-asyncio; extra == "test"
Provides-Extra: lint
Requires-Dist: pylint; extra == "lint"
Dynamic: license-file
